simpl_kafka_wrapper/__init__.py
simpl_kafka_wrapper/exceptions/__init__.py
simpl_kafka_wrapper/exceptions/custom_base_exception.py
simpl_kafka_wrapper/exceptions/event_schema_mismatch_exception.py
simpl_kafka_wrapper/exceptions/invalid_event_class_exception.py
simpl_kafka_wrapper/models/__init__.py
simpl_kafka_wrapper/models/configs/__init__.py
simpl_kafka_wrapper/models/configs/kafka/__init__.py
simpl_kafka_wrapper/models/configs/kafka/kafka_config.py
simpl_kafka_wrapper/models/events/__init__.py
simpl_kafka_wrapper/models/events/base_event.py
simpl_kafka_wrapper/producer.py
simpl_kafka_wrapper/utils/__init__.py
simpl_kafka_wrapper/utils/logger.py
simpl_kafka_wrapper/utils/singleton.py
simpl_kafka_wrapper-0.2.3.dist-info/METADATA
simpl_kafka_wrapper-0.2.3.dist-info/WHEEL
simpl_kafka_wrapper-0.2.3.dist-info/RECORD
