Metadata-Version: 2.1
Name: simpl-kafka-wrapper
Version: 0.2.3
Summary: Confluent kafka Wrapper to publish messages to Kafka broker with a defined Structure
Author: Somil Singhai
Author-email: somil.singhai@getsimpl.com
Requires-Python: >=3.8,<4.0
Classifier: Programming Language :: Python :: 3
Classifier: Programming Language :: Python :: 3.8
Classifier: Programming Language :: Python :: 3.9
Classifier: Programming Language :: Python :: 3.10
Classifier: Programming Language :: Python :: 3.11
Requires-Dist: confluent-kafka (>=1.9.0,<2.0.0)
Requires-Dist: pydantic (>=2.3.0,<3.0.0)
Requires-Dist: pytz (>=2023.3,<2024.0)
Requires-Dist: structlog (>=22.1.0,<23.0.0)
